_fastscapelib_py.cp313-win_amd64.pyd
fastscapelib/__init__.py
fastscapelib/eroders/__init__.py
fastscapelib/eroders/__init__.pyi
fastscapelib/eroders/flow_kernel_eroder.py
fastscapelib/flow/__init__.py
fastscapelib/flow/__init__.pyi
fastscapelib/flow/numba/__init__.py
fastscapelib/flow/numba/flow_kernel.py
fastscapelib/grid/__init__.py
fastscapelib/grid/__init__.pyi
fastscapelib/tests/test_eroders.py
fastscapelib/tests/test_flow_graph.py
fastscapelib/tests/test_flow_kernel.py
fastscapelib/tests/test_flow_kernel_eroder.py
fastscapelib/tests/test_flow_router.py
fastscapelib/tests/test_flow_snapshot.py
fastscapelib/tests/test_healpix_grid.py
fastscapelib/tests/test_profile_grid.py
fastscapelib/tests/test_raster_grid.py
fastscapelib/tests/test_sink_resolver.py
fastscapelib/tests/test_trimesh.py
fastscapelib-0.3.0.dist-info/METADATA
fastscapelib-0.3.0.dist-info/WHEEL
fastscapelib-0.3.0.dist-info/licenses/LICENSE
fastscapelib-0.3.0.dist-info/RECORD
