Metadata-Version: 2.2
Name: fastscapelib
Version: 0.3.0
Summary: A C++/Python library of efficient algorithms for landscape evolution modeling
Keywords: modeling,topography,geomorphology,landscape-evolution
Author: Benoît Bovy
Maintainer: Fastscapelib contributors
License: GPL-3.0 license
Project-URL: Home, https://fastscapelib.readthedocs.io
Project-URL: Repository, https://github.com/fastscape-lem/fastscapelib
Requires-Python: >=3.10
Requires-Dist: numpy>=1.24
Provides-Extra: numba
Requires-Dist: numba; extra == "numba"
Provides-Extra: test
Requires-Dist: pytest>=6.0; extra == "test"
